snipit/__init__.py
snipit/command.py
snipit/scripts/__init__.py
snipit/scripts/snp_functions.py
snipit-1.7.dist-info/licenses/LICENSE
snipit-1.7.dist-info/METADATA
snipit-1.7.dist-info/WHEEL
snipit-1.7.dist-info/entry_points.txt
snipit-1.7.dist-info/top_level.txt
snipit-1.7.dist-info/RECORD
