Metadata-Version: 2.4
Name: snipit
Version: 1.7
Summary: snipit
Author-email: Aine OToole <aine.otoole@ed.ac.uk>
License: LICENSE
Project-URL: Homepage, https://github.com/aineniamh/snipit
Requires-Python: >=3.9
License-File: LICENSE
Requires-Dist: biopython>=1.78
Requires-Dist: matplotlib>=3.5
Dynamic: license-file
